tnn/__init__.py
tnn/datasets/__init__.py
tnn/datasets/mnist.py
tnn/datasets/nabirds.py
tnn/datasets/transforms.py
tnn/layers/__init__.py
tnn/layers/similarity.py
tnn/layers/tversky_layer.py
tnn/models/__init__.py
tnn/models/base.py
tnn/models/resnet.py
tnn/training/__init__.py
tnn/training/config.py
tnn/training/metrics.py
tnn/training/trainer.py
tnn/utils/__init__.py
tnn/utils/data_utils.py
tnn/utils/visualization.py
tversky_nn-1.0.1.dist-info/licenses/LICENSE
tversky_nn-1.0.1.dist-info/METADATA
tversky_nn-1.0.1.dist-info/WHEEL
tversky_nn-1.0.1.dist-info/top_level.txt
tversky_nn-1.0.1.dist-info/RECORD
