Metadata-Version: 2.4
Name: tversky-nn
Version: 1.0.1
Summary: My faithful reproduction of Tversky Neural Networks (TNNs)
Author-email: Akshath Mangudi <akshathmangudi@gmail.com>
License: MIT
Project-URL: Homepage, https://github.com/akshathmangudi/tnn
Project-URL: Repository, https://github.com/akshathmangudi/tnn
Project-URL: Issues, https://github.com/akshathmangudi/tnn/issues
Keywords: deep-learning,pytorch,tversky,neural-networks,xai,ml
Classifier: Development Status :: 3 - Alpha
Classifier: Intended Audience :: Science/Research
Classifier: License :: OSI Approved :: MIT License
Classifier: Programming Language :: Python :: 3
Classifier: Topic :: Scientific/Engineering :: Artificial Intelligence
Requires-Python: >=3.10
License-File: LICENSE
Requires-Dist: torch>=2.0.0
Requires-Dist: torchvision>=0.15.0
Requires-Dist: transformers>=4.39.0
Requires-Dist: numpy
Requires-Dist: tqdm
Requires-Dist: scikit-learn
Requires-Dist: pillow
Requires-Dist: matplotlib
Requires-Dist: seaborn
Provides-Extra: dev
Requires-Dist: pytest; extra == "dev"
Requires-Dist: black; extra == "dev"
Requires-Dist: ruff; extra == "dev"
Requires-Dist: isort; extra == "dev"
Requires-Dist: mypy; extra == "dev"
Requires-Dist: jupyter; extra == "dev"
Provides-Extra: viz
Requires-Dist: matplotlib; extra == "viz"
Requires-Dist: seaborn; extra == "viz"
Provides-Extra: xai
Requires-Dist: captum; extra == "xai"
Requires-Dist: shap; extra == "xai"
Requires-Dist: lime; extra == "xai"
Provides-Extra: bench
Requires-Dist: wandb; extra == "bench"
Requires-Dist: tensorboard; extra == "bench"
Dynamic: license-file
